target365_sdk/__init__.py
target365_sdk/api_client.py
target365_sdk/helpers/__init__.py
target365_sdk/helpers/http_client.py
target365_sdk/models/__init__.py
target365_sdk/models/delivery_report.py
target365_sdk/models/detailed_status_codes.py
target365_sdk/models/in_message.py
target365_sdk/models/keyword.py
target365_sdk/models/keyword_preauth_settings.py
target365_sdk/models/lookup_result.py
target365_sdk/models/model.py
target365_sdk/models/one_time_password.py
target365_sdk/models/oneclick_config.py
target365_sdk/models/out_message.py
target365_sdk/models/out_message_strex.py
target365_sdk/models/pincode.py
target365_sdk/models/public_key.py
target365_sdk/models/status_codes.py
target365_sdk/models/strex_merchant.py
target365_sdk/models/strex_registration_sms.py
target365_sdk/models/strex_transaction.py
target365_sdk/models/user_validity.py
target365_sdk/tests/__init__.py
target365_sdk/tests/test_api_client.py
target365_sdk-1.8.5.dist-info/LICENSE
target365_sdk-1.8.5.dist-info/METADATA
target365_sdk-1.8.5.dist-info/WHEEL
target365_sdk-1.8.5.dist-info/top_level.txt
target365_sdk-1.8.5.dist-info/RECORD
